{
  "54ezfr0v": "искусственная кожа",
  "oggo0m7qeay34xkp": "поліефірне волокно",
  "iyaoejjgbfbvvhom": "байка",
  "f0ooxfxiciamggn8": "холлофайбер",
  "eyvftk3hf2ejkz2r": "екозамша",
  "vrwj3yvc3ebhvn5w": "плюш",
  "ts9bss7bltluxeap": "полипропилен",
  "b7owcz7awgrqtom8": "текстиль",
  "iaykawfa": "хлопок",
  "1dailngf": "ткань",
  "bblyi2ri": "велюр",
  "tmh5xv4g": "полиэстер",
  "za1xmuby": "кожа",
  "t1clkbhe": "полиуретан",
  "bycsvdto": "ПВХ",
  "bddpkeja": "алькантара",
  "skgiioa7qvkkctag": "екошкіра"
}