{
  "72171dc6c6db0d7c67f2cb2aac89ec4a": "желтый с голубым",
  "685": "темно-серый",
  "dce530436d659e2a255365a55555a014": "желтый с синим",
  "664": "чорний із червоним",
  "669": "чорний із білим",
  "691": "желто-черный",
  "695": "світло-сірий",
  "713": "червоний із чорним",
  "a3974c8c5fb2f5b9d525b4859de8d5a0": "темно-синий",
  "rty37clq": "бірюзовий",
  "u2rqrf0q": "голубой",
  "ophru6z8": "білий",
  "e3fyw7jf": "бежевий",
  "ji7xemhv": "жовтий",
  "zbjmtjbl": "коричневий",
  "lcjfhn4e": "оранжевый",
  "5uooq3p5": "красный",
  "kd4hovsb": "зеленый",
  "nlmlmqnr": "розовый",
  "gsyiryzw": "серый",
  "ct2lhsxt": "фіолетовий",
  "roiaf3xb": "синій",
  "2gnuojuhhguggjne": "капучино",
  "ghdrzpt0vuqtj18h": "медь",
  "ff8cwdpi": "чорний",
  "hbac10n7": "бордовий",
  "hbrprb2v": "різнокольоровий",
  "t87zfctb": "кремовий",
  "vp1446301075g7k3": "темно-зеленый",
  "ysdm2cikxtm5cm7q": "блакитний із жовтим",
  "qsdnizm4nv4wy5ng": "синий с желтым",
  "ac52dc0163f15ed64f69a87f37cb524f": "смарагдовий"
}